{
  "_meta": {
    "createdBy": "DataMiner",
    "createdAt": "2026-05-27T22:48:49.641Z",
    "fileName": "etf_prices_20260528.json"
  },
  "data": {
    "source": "DATA_GO_KR",
    "isRealData": true,
    "fetchedAt": "2026-05-27T22:48:49.640Z",
    "baseDate": "20260526",
    "etfCount": 100,
    "etfList": [
      {
        "code": "0000D0",
        "name": "TIGER 엔비디아미국채커버드콜밸런스(합성)",
        "price": 10265,
        "change": -75,
        "changeRate": -0.73,
        "volume": 148240,
        "tradeAmount": 1524068456,
        "marketCap": 71855000000,
        "nav": 10255.4,
        "highPrice": 10375,
        "lowPrice": 10240,
        "openPrice": 10375,
        "date": "20260526",
        "sector": "커버드콜·월배당"
      },
      {
        "code": "0000H0",
        "name": "KODEX 인도Nifty미드캡100",
        "price": 11320,
        "change": 160,
        "changeRate": 1.43,
        "volume": 6308,
        "tradeAmount": 71276395,
        "marketCap": 16414000000,
        "nav": 11250.56,
        "highPrice": 11385,
        "lowPrice": 11200,
        "openPrice": 11225,
        "date": "20260526",
        "sector": "기타"
      },
      {
        "code": "0000J0",
        "name": "PLUS 한화그룹주",
        "price": 39325,
        "change": 1560,
        "changeRate": 4.13,
        "volume": 230034,
        "tradeAmount": 8949907453,
        "marketCap": 232017500000,
        "nav": 39332.42,
        "highPrice": 39595,
        "lowPrice": 37820,
        "openPrice": 38315,
        "date": "20260526",
        "sector": "기타"
      },
      {
        "code": "0000Y0",
        "name": "HK 26-12 회사채(AA-이상)액티브",
        "price": 101105,
        "change": -30,
        "changeRate": -0.03,
        "volume": 33,
        "tradeAmount": 3336300,
        "marketCap": 122337050000,
        "nav": 101116.2,
        "highPrice": 101135,
        "lowPrice": 101090,
        "openPrice": 101090,
        "date": "20260526",
        "sector": "채권"
      },
      {
        "code": "0000Z0",
        "name": "RISE 바이오TOP10액티브",
        "price": 13590,
        "change": 175,
        "changeRate": 1.3,
        "volume": 439089,
        "tradeAmount": 6045302598,
        "marketCap": 98527500000,
        "nav": 13544.34,
        "highPrice": 14130,
        "lowPrice": 13450,
        "openPrice": 13925,
        "date": "20260526",
        "sector": "기타"
      },
      {
        "code": "0001P0",
        "name": "마이티 바이오시밀러&CDMO액티브",
        "price": 11500,
        "change": -155,
        "changeRate": -1.33,
        "volume": 15141,
        "tradeAmount": 175843425,
        "marketCap": 12880000000,
        "nav": 11542.59,
        "highPrice": 11895,
        "lowPrice": 11485,
        "openPrice": 11825,
        "date": "20260526",
        "sector": "기타"
      },
      {
        "code": "0002C0",
        "name": "에셋플러스 인도일등기업포커스20액티브",
        "price": 10000,
        "change": 70,
        "changeRate": 0.7,
        "volume": 4050,
        "tradeAmount": 40378890,
        "marketCap": 10800000000,
        "nav": 9993.52,
        "highPrice": 10050,
        "lowPrice": 9880,
        "openPrice": 9930,
        "date": "20260526",
        "sector": "기타"
      },
      {
        "code": "0004G0",
        "name": "1Q 미국배당TOP30",
        "price": 9325,
        "change": 105,
        "changeRate": 1.14,
        "volume": 44926,
        "tradeAmount": 419521361,
        "marketCap": 13055000000,
        "nav": 9271.55,
        "highPrice": 9365,
        "lowPrice": 9310,
        "openPrice": 9355,
        "date": "20260526",
        "sector": "해외주식"
      },
      {
        "code": "0005A0",
        "name": "KODEX 미국S&P500데일리커버드콜OTM",
        "price": 10605,
        "change": -15,
        "changeRate": -0.14,
        "volume": 385711,
        "tradeAmount": 4104423633,
        "marketCap": 173922000000,
        "nav": 10499.37,
        "highPrice": 10705,
        "lowPrice": 10595,
        "openPrice": 10650,
        "date": "20260526",
        "sector": "커버드콜·월배당"
      },
      {
        "code": "0005C0",
        "name": "RISE 미국S&P500엔화노출(합성 H)",
        "price": 12120,
        "change": 100,
        "changeRate": 0.83,
        "volume": 3236,
        "tradeAmount": 39203950,
        "marketCap": 9696000000,
        "nav": 12000.63,
        "highPrice": 12160,
        "lowPrice": 12092,
        "openPrice": 12100,
        "date": "20260526",
        "sector": "해외주식"
      },
      {
        "code": "0005D0",
        "name": "SOL 전고체배터리&실리콘음극재",
        "price": 22885,
        "change": -90,
        "changeRate": -0.39,
        "volume": 884454,
        "tradeAmount": 20562489460,
        "marketCap": 224273000000,
        "nav": 22890.66,
        "highPrice": 23795,
        "lowPrice": 22830,
        "openPrice": 23510,
        "date": "20260526",
        "sector": "2차전지"
      },
      {
        "code": "0005G0",
        "name": "IBK K-AI반도체코어테크",
        "price": 62915,
        "change": 5715,
        "changeRate": 9.99,
        "volume": 202811,
        "tradeAmount": 12734934939,
        "marketCap": 191890750000,
        "nav": 62614.82,
        "highPrice": 63720,
        "lowPrice": 60335,
        "openPrice": 60740,
        "date": "20260526",
        "sector": "AI·데이터"
      },
      {
        "code": "0007F0",
        "name": "KODEX 27-12 회사채(AA-이상)액티브",
        "price": 10135,
        "change": 5,
        "changeRate": 0.05,
        "volume": 37518,
        "tradeAmount": 380010242,
        "marketCap": 581647650000,
        "nav": 10120.81,
        "highPrice": 10135,
        "lowPrice": 10120,
        "openPrice": 10130,
        "date": "20260526",
        "sector": "채권"
      },
      {
        "code": "0007G0",
        "name": "PLUS 글로벌원자력밸류체인",
        "price": 16150,
        "change": 50,
        "changeRate": 0.31,
        "volume": 32237,
        "tradeAmount": 523318663,
        "marketCap": 54102500000,
        "nav": 16018.19,
        "highPrice": 16460,
        "lowPrice": 16100,
        "openPrice": 16100,
        "date": "20260526",
        "sector": "기타"
      },
      {
        "code": "0007N0",
        "name": "아이엠에셋 200",
        "price": 127640,
        "change": 3470,
        "changeRate": 2.79,
        "volume": 241,
        "tradeAmount": 30759710,
        "marketCap": 114876000000,
        "nav": 127296.77,
        "highPrice": 129070,
        "lowPrice": 126290,
        "openPrice": 126935,
        "date": "20260526",
        "sector": "기타"
      },
      {
        "code": "0008E0",
        "name": "ACE 미국중심중소형제조업",
        "price": 14915,
        "change": 295,
        "changeRate": 2.02,
        "volume": 85305,
        "tradeAmount": 1272576445,
        "marketCap": 13423500000,
        "nav": 14644.99,
        "highPrice": 15085,
        "lowPrice": 14770,
        "openPrice": 14830,
        "date": "20260526",
        "sector": "해외주식"
      },
      {
        "code": "0008S0",
        "name": "TIGER 미국배당다우존스타겟데일리커버드콜",
        "price": 10690,
        "change": 130,
        "changeRate": 1.23,
        "volume": 329360,
        "tradeAmount": 3525961364,
        "marketCap": 244266500000,
        "nav": 10631.64,
        "highPrice": 10735,
        "lowPrice": 10675,
        "openPrice": 10725,
        "date": "20260526",
        "sector": "커버드콜·월배당"
      },
      {
        "code": "0008T0",
        "name": "SOL 화장품TOP3플러스",
        "price": 14665,
        "change": -135,
        "changeRate": -0.91,
        "volume": 502380,
        "tradeAmount": 7443317988,
        "marketCap": 66725750000,
        "nav": 14681.36,
        "highPrice": 15200,
        "lowPrice": 14590,
        "openPrice": 15085,
        "date": "20260526",
        "sector": "기타"
      },
      {
        "code": "0013P0",
        "name": "RISE 미국은행TOP10",
        "price": 12350,
        "change": -20,
        "changeRate": -0.16,
        "volume": 22773,
        "tradeAmount": 282681977,
        "marketCap": 16055000000,
        "nav": 12312.48,
        "highPrice": 12500,
        "lowPrice": 12350,
        "openPrice": 12500,
        "date": "20260526",
        "sector": "해외주식"
      },
      {
        "code": "0013R0",
        "name": "RISE 테슬라미국채타겟커버드콜혼합(합성)",
        "price": 9475,
        "change": -65,
        "changeRate": -0.68,
        "volume": 144591,
        "tradeAmount": 1380699182,
        "marketCap": 36005000000,
        "nav": 9464.15,
        "highPrice": 9595,
        "lowPrice": 9475,
        "openPrice": 9540,
        "date": "20260526",
        "sector": "커버드콜·월배당"
      },
      {
        "code": "0015B0",
        "name": "KoAct 미국나스닥성장기업액티브",
        "price": 23645,
        "change": 105,
        "changeRate": 0.45,
        "volume": 1087006,
        "tradeAmount": 25848837105,
        "marketCap": 651419750000,
        "nav": 23234.16,
        "highPrice": 24025,
        "lowPrice": 23605,
        "openPrice": 23765,
        "date": "20260526",
        "sector": "해외주식"
      },
      {
        "code": "0015E0",
        "name": "KIWOOM 엔비디아미국30년국채혼합액티브(H)",
        "price": 10730,
        "change": 30,
        "changeRate": 0.28,
        "volume": 12228,
        "tradeAmount": 131052462,
        "marketCap": 5365000000,
        "nav": 10791.37,
        "highPrice": 10735,
        "lowPrice": 10700,
        "openPrice": 10700,
        "date": "20260526",
        "sector": "해외주식"
      },
      {
        "code": "0015F0",
        "name": "KIWOOM 팔란티어미국30년국채혼합액티브(H)",
        "price": 10030,
        "change": 10,
        "changeRate": 0.1,
        "volume": 38664,
        "tradeAmount": 387794490,
        "marketCap": 17051000000,
        "nav": 10103.12,
        "highPrice": 10060,
        "lowPrice": 9950,
        "openPrice": 9950,
        "date": "20260526",
        "sector": "AI·데이터"
      },
      {
        "code": "0015K0",
        "name": "TIGER 미국소비트렌드액티브",
        "price": 7685,
        "change": -20,
        "changeRate": -0.26,
        "volume": 2878,
        "tradeAmount": 22132135,
        "marketCap": 4841550000,
        "nav": 7660.32,
        "highPrice": 7770,
        "lowPrice": 7685,
        "openPrice": 7705,
        "date": "20260526",
        "sector": "해외주식"
      },
      {
        "code": "0016X0",
        "name": "SOL 중단기회사채(A-이상)액티브",
        "price": 51060,
        "change": 35,
        "changeRate": 0.07,
        "volume": 6068,
        "tradeAmount": 309748395,
        "marketCap": 419713200000,
        "nav": 51058.57,
        "highPrice": 51060,
        "lowPrice": 51040,
        "openPrice": 51050,
        "date": "20260526",
        "sector": "채권"
      },
      {
        "code": "0017Y0",
        "name": "1Q 종합채권(AA-이상)액티브",
        "price": 94925,
        "change": 320,
        "changeRate": 0.34,
        "volume": 1143,
        "tradeAmount": 108453720,
        "marketCap": 85622350000,
        "nav": 94889.86,
        "highPrice": 95000,
        "lowPrice": 94815,
        "openPrice": 94960,
        "date": "20260526",
        "sector": "채권"
      },
      {
        "code": "0018C0",
        "name": "PLUS 고배당주위클리고정커버드콜",
        "price": 12020,
        "change": -150,
        "changeRate": -1.23,
        "volume": 300324,
        "tradeAmount": 3626872722,
        "marketCap": 96160000000,
        "nav": 12113.01,
        "highPrice": 12350,
        "lowPrice": 12000,
        "openPrice": 12285,
        "date": "20260526",
        "sector": "커버드콜·월배당"
      },
      {
        "code": "0018Z0",
        "name": "RISE 미국양자컴퓨팅",
        "price": 22455,
        "change": 935,
        "changeRate": 4.34,
        "volume": 49589,
        "tradeAmount": 1117263225,
        "marketCap": 20209500000,
        "nav": 21887.37,
        "highPrice": 22810,
        "lowPrice": 22205,
        "openPrice": 22615,
        "date": "20260526",
        "sector": "해외주식"
      },
      {
        "code": "0019K0",
        "name": "TIME 미국나스닥100채권혼합50액티브",
        "price": 14325,
        "change": 30,
        "changeRate": 0.21,
        "volume": 1270509,
        "tradeAmount": 18281583539,
        "marketCap": 348813750000,
        "nav": 14179.47,
        "highPrice": 14690,
        "lowPrice": 14275,
        "openPrice": 14495,
        "date": "20260526",
        "sector": "해외주식"
      },
      {
        "code": "0020H0",
        "name": "KoAct 글로벌양자컴퓨팅액티브",
        "price": 30775,
        "change": 1680,
        "changeRate": 5.77,
        "volume": 269924,
        "tradeAmount": 8357334879,
        "marketCap": 55395000000,
        "nav": 29886.24,
        "highPrice": 36215,
        "lowPrice": 30440,
        "openPrice": 32000,
        "date": "20260526",
        "sector": "기타"
      },
      {
        "code": "0021C0",
        "name": "ACE TDF장기자산배분액티브",
        "price": 14455,
        "change": 55,
        "changeRate": 0.38,
        "volume": 9528,
        "tradeAmount": 138054197,
        "marketCap": 13732250000,
        "nav": 14309.08,
        "highPrice": 14570,
        "lowPrice": 14300,
        "openPrice": 14400,
        "date": "20260526",
        "sector": "기타"
      },
      {
        "code": "0021D0",
        "name": "ACE TDF2030액티브 적격",
        "price": 11485,
        "change": 15,
        "changeRate": 0.13,
        "volume": 11482,
        "tradeAmount": 132565740,
        "marketCap": 16653250000,
        "nav": 11480.46,
        "highPrice": 11630,
        "lowPrice": 11380,
        "openPrice": 11560,
        "date": "20260526",
        "sector": "기타"
      },
      {
        "code": "0021E0",
        "name": "ACE TDF2050액티브 적격",
        "price": 13170,
        "change": 45,
        "changeRate": 0.34,
        "volume": 50589,
        "tradeAmount": 664608260,
        "marketCap": 66508500000,
        "nav": 13067.97,
        "highPrice": 13280,
        "lowPrice": 12985,
        "openPrice": 13115,
        "date": "20260526",
        "sector": "기타"
      },
      {
        "code": "0022T0",
        "name": "SOL 국제금커버드콜액티브",
        "price": 14965,
        "change": -115,
        "changeRate": -0.76,
        "volume": 156314,
        "tradeAmount": 2354618732,
        "marketCap": 83804000000,
        "nav": 14891.06,
        "highPrice": 15140,
        "lowPrice": 14955,
        "openPrice": 15140,
        "date": "20260526",
        "sector": "커버드콜·월배당"
      },
      {
        "code": "0023A0",
        "name": "SOL 미국양자컴퓨팅TOP10",
        "price": 38440,
        "change": 1980,
        "changeRate": 5.43,
        "volume": 1591591,
        "tradeAmount": 61403715408,
        "marketCap": 584288000000,
        "nav": 37529.93,
        "highPrice": 39235,
        "lowPrice": 37835,
        "openPrice": 38800,
        "date": "20260526",
        "sector": "해외주식"
      },
      {
        "code": "0023B0",
        "name": "PLUS 미국양자컴퓨팅TOP10",
        "price": 22665,
        "change": 1015,
        "changeRate": 4.69,
        "volume": 220294,
        "tradeAmount": 5017743157,
        "marketCap": 43063500000,
        "nav": 22077.29,
        "highPrice": 23030,
        "lowPrice": 21970,
        "openPrice": 22400,
        "date": "20260526",
        "sector": "해외주식"
      },
      {
        "code": "0025N0",
        "name": "TIGER TDF2045 적격",
        "price": 12665,
        "change": 10,
        "changeRate": 0.08,
        "volume": 713733,
        "tradeAmount": 9059913366,
        "marketCap": 702274250000,
        "nav": 12552,
        "highPrice": 12725,
        "lowPrice": 12665,
        "openPrice": 12705,
        "date": "20260526",
        "sector": "기타"
      },
      {
        "code": "0026E0",
        "name": "KODEX 미국S&P500버퍼3월액티브",
        "price": 12375,
        "change": -105,
        "changeRate": -0.84,
        "volume": 1852,
        "tradeAmount": 22979925,
        "marketCap": 22893750000,
        "nav": 12416.46,
        "highPrice": 12510,
        "lowPrice": 12375,
        "openPrice": 12510,
        "date": "20260526",
        "sector": "해외주식"
      },
      {
        "code": "0026S0",
        "name": "1Q 미국S&P500",
        "price": 13750,
        "change": -5,
        "changeRate": -0.04,
        "volume": 306146,
        "tradeAmount": 4221551548,
        "marketCap": 305250000000,
        "nav": 13653.76,
        "highPrice": 13870,
        "lowPrice": 13740,
        "openPrice": 13835,
        "date": "20260526",
        "sector": "해외주식"
      },
      {
        "code": "0028X0",
        "name": "KODEX 미국금융테크액티브",
        "price": 11300,
        "change": -100,
        "changeRate": -0.88,
        "volume": 9763,
        "tradeAmount": 110389472,
        "marketCap": 18080000000,
        "nav": 11236.78,
        "highPrice": 11400,
        "lowPrice": 11300,
        "openPrice": 11400,
        "date": "20260526",
        "sector": "해외주식"
      },
      {
        "code": "0035T0",
        "name": "PLUS 글로벌휴머노이드로봇액티브",
        "price": 25770,
        "change": 1050,
        "changeRate": 4.25,
        "volume": 178800,
        "tradeAmount": 4591316454,
        "marketCap": 139158000000,
        "nav": 25503.42,
        "highPrice": 25835,
        "lowPrice": 25380,
        "openPrice": 25500,
        "date": "20260526",
        "sector": "기타"
      },
      {
        "code": "0036D0",
        "name": "TIME 미국배당다우존스액티브",
        "price": 13525,
        "change": 220,
        "changeRate": 1.65,
        "volume": 98734,
        "tradeAmount": 1335933001,
        "marketCap": 52071250000,
        "nav": 13355.45,
        "highPrice": 13700,
        "lowPrice": 13315,
        "openPrice": 13430,
        "date": "20260526",
        "sector": "커버드콜·월배당"
      },
      {
        "code": "0036R0",
        "name": "RISE 미국휴머노이드로봇",
        "price": 22455,
        "change": 335,
        "changeRate": 1.51,
        "volume": 160799,
        "tradeAmount": 3618642564,
        "marketCap": 124625250000,
        "nav": 22110.7,
        "highPrice": 22615,
        "lowPrice": 22325,
        "openPrice": 22450,
        "date": "20260526",
        "sector": "해외주식"
      },
      {
        "code": "0036Z0",
        "name": "RISE 미국천연가스밸류체인",
        "price": 14220,
        "change": 40,
        "changeRate": 0.28,
        "volume": 8065,
        "tradeAmount": 114479387,
        "marketCap": 9954000000,
        "nav": 14210.59,
        "highPrice": 15000,
        "lowPrice": 14140,
        "openPrice": 15000,
        "date": "20260526",
        "sector": "해외주식"
      },
      {
        "code": "0038A0",
        "name": "KODEX 미국휴머노이드로봇",
        "price": 18660,
        "change": 190,
        "changeRate": 1.03,
        "volume": 255984,
        "tradeAmount": 4789010154,
        "marketCap": 335880000000,
        "nav": 18446.33,
        "highPrice": 18790,
        "lowPrice": 18640,
        "openPrice": 18755,
        "date": "20260526",
        "sector": "해외주식"
      },
      {
        "code": "0040S0",
        "name": "HANARO 글로벌피지컬AI액티브",
        "price": 29250,
        "change": 635,
        "changeRate": 2.22,
        "volume": 109325,
        "tradeAmount": 3200505115,
        "marketCap": 70200000000,
        "nav": 28566.71,
        "highPrice": 29410,
        "lowPrice": 28780,
        "openPrice": 28780,
        "date": "20260526",
        "sector": "AI·데이터"
      },
      {
        "code": "0040X0",
        "name": "SOL 팔란티어미국채커버드콜혼합",
        "price": 9975,
        "change": -45,
        "changeRate": -0.45,
        "volume": 476220,
        "tradeAmount": 4761433180,
        "marketCap": 221445000000,
        "nav": 9977.69,
        "highPrice": 10055,
        "lowPrice": 9970,
        "openPrice": 10015,
        "date": "20260526",
        "sector": "AI·데이터"
      },
      {
        "code": "0040Y0",
        "name": "SOL 팔란티어커버드콜OTM채권혼합",
        "price": 8790,
        "change": 20,
        "changeRate": 0.23,
        "volume": 1134387,
        "tradeAmount": 9973154412,
        "marketCap": 394231500000,
        "nav": 8724.14,
        "highPrice": 8825,
        "lowPrice": 8770,
        "openPrice": 8770,
        "date": "20260526",
        "sector": "AI·데이터"
      },
      {
        "code": "0041D0",
        "name": "KODEX 미국AI소프트웨어TOP10",
        "price": 12995,
        "change": -35,
        "changeRate": -0.27,
        "volume": 65517,
        "tradeAmount": 854107026,
        "marketCap": 62376000000,
        "nav": 12897.89,
        "highPrice": 13145,
        "lowPrice": 12980,
        "openPrice": 13145,
        "date": "20260526",
        "sector": "AI·데이터"
      },
      {
        "code": "0041E0",
        "name": "KODEX 미국S&P500액티브",
        "price": 18025,
        "change": 50,
        "changeRate": 0.28,
        "volume": 263535,
        "tradeAmount": 4762055998,
        "marketCap": 124372500000,
        "nav": 17893.41,
        "highPrice": 18800,
        "lowPrice": 17975,
        "openPrice": 18050,
        "date": "20260526",
        "sector": "해외주식"
      },
      {
        "code": "0043B0",
        "name": "TIGER 머니마켓액티브",
        "price": 102555,
        "change": 5,
        "changeRate": 0,
        "volume": 153270,
        "tradeAmount": 15718834792,
        "marketCap": 3025064835000,
        "nav": 102547.43,
        "highPrice": 102560,
        "lowPrice": 102555,
        "openPrice": 102555,
        "date": "20260526",
        "sector": "기타"
      },
      {
        "code": "0043Y0",
        "name": "TIME 차이나AI테크액티브",
        "price": 24450,
        "change": 1355,
        "changeRate": 5.87,
        "volume": 642216,
        "tradeAmount": 15645588631,
        "marketCap": 348412500000,
        "nav": 23783.58,
        "highPrice": 24750,
        "lowPrice": 23800,
        "openPrice": 23900,
        "date": "20260526",
        "sector": "AI·데이터"
      },
      {
        "code": "0046A0",
        "name": "TIGER 미국초단기(3개월이하)국채",
        "price": 10420,
        "change": -90,
        "changeRate": -0.86,
        "volume": 1425877,
        "tradeAmount": 14916364651,
        "marketCap": 375015800000,
        "nav": 10419.38,
        "highPrice": 10495,
        "lowPrice": 10420,
        "openPrice": 10480,
        "date": "20260526",
        "sector": "해외주식"
      },
      {
        "code": "0046Y0",
        "name": "ACE 미국배당퀄리티",
        "price": 13440,
        "change": 25,
        "changeRate": 0.19,
        "volume": 18256,
        "tradeAmount": 246285510,
        "marketCap": 55776000000,
        "nav": 13341.64,
        "highPrice": 13565,
        "lowPrice": 13415,
        "openPrice": 13415,
        "date": "20260526",
        "sector": "해외주식"
      },
      {
        "code": "0047A0",
        "name": "TIGER 차이나테크TOP10",
        "price": 15580,
        "change": 520,
        "changeRate": 3.45,
        "volume": 358397,
        "tradeAmount": 5561113801,
        "marketCap": 281998000000,
        "nav": 15388.08,
        "highPrice": 15890,
        "lowPrice": 15225,
        "openPrice": 15240,
        "date": "20260526",
        "sector": "기타"
      },
      {
        "code": "0047N0",
        "name": "PLUS 차이나AI테크TOP10",
        "price": 11485,
        "change": -60,
        "changeRate": -0.52,
        "volume": 17446,
        "tradeAmount": 202408780,
        "marketCap": 11485000000,
        "nav": 11480.77,
        "highPrice": 11905,
        "lowPrice": 11465,
        "openPrice": 11575,
        "date": "20260526",
        "sector": "AI·데이터"
      },
      {
        "code": "0047P0",
        "name": "RISE 테슬라고정테크100",
        "price": 16460,
        "change": 270,
        "changeRate": 1.67,
        "volume": 30002,
        "tradeAmount": 494214015,
        "marketCap": 24690000000,
        "nav": 16217.47,
        "highPrice": 16575,
        "lowPrice": 16440,
        "openPrice": 16440,
        "date": "20260526",
        "sector": "기타"
      },
      {
        "code": "0047R0",
        "name": "RISE 팔란티어고정테크100",
        "price": 15445,
        "change": 15,
        "changeRate": 0.1,
        "volume": 25101,
        "tradeAmount": 388782521,
        "marketCap": 33979000000,
        "nav": 15383.37,
        "highPrice": 15735,
        "lowPrice": 15445,
        "openPrice": 15735,
        "date": "20260526",
        "sector": "AI·데이터"
      },
      {
        "code": "0048J0",
        "name": "KODEX 미국머니마켓액티브",
        "price": 15080,
        "change": -105,
        "changeRate": -0.69,
        "volume": 578448,
        "tradeAmount": 8751653340,
        "marketCap": 690664000000,
        "nav": 15076.23,
        "highPrice": 15190,
        "lowPrice": 15075,
        "openPrice": 15190,
        "date": "20260526",
        "sector": "해외주식"
      },
      {
        "code": "0048K0",
        "name": "KODEX 차이나휴머노이드로봇",
        "price": 12280,
        "change": -35,
        "changeRate": -0.28,
        "volume": 1321065,
        "tradeAmount": 16374761993,
        "marketCap": 259108000000,
        "nav": 12223.61,
        "highPrice": 12700,
        "lowPrice": 12130,
        "openPrice": 12405,
        "date": "20260526",
        "sector": "기타"
      },
      {
        "code": "0049K0",
        "name": "ACE 미국배당퀄리티채권혼합50",
        "price": 11600,
        "change": 20,
        "changeRate": 0.17,
        "volume": 25525,
        "tradeAmount": 296163257,
        "marketCap": 23200000000,
        "nav": 11498.28,
        "highPrice": 11625,
        "lowPrice": 11580,
        "openPrice": 11590,
        "date": "20260526",
        "sector": "해외주식"
      },
      {
        "code": "0049M0",
        "name": "ACE 미국배당퀄리티+커버드콜액티브",
        "price": 12330,
        "change": 40,
        "changeRate": 0.33,
        "volume": 50511,
        "tradeAmount": 622758914,
        "marketCap": 88776000000,
        "nav": 12185.99,
        "highPrice": 12355,
        "lowPrice": 12290,
        "openPrice": 12290,
        "date": "20260526",
        "sector": "커버드콜·월배당"
      },
      {
        "code": "0050E0",
        "name": "PLUS 미국AI에이전트",
        "price": 8600,
        "change": 50,
        "changeRate": 0.58,
        "volume": 8646,
        "tradeAmount": 74503487,
        "marketCap": 4730000000,
        "nav": 8558.95,
        "highPrice": 8890,
        "lowPrice": 8430,
        "openPrice": 8550,
        "date": "20260526",
        "sector": "AI·데이터"
      },
      {
        "code": "0051A0",
        "name": "KoAct 브로드컴밸류체인액티브",
        "price": 27270,
        "change": 440,
        "changeRate": 1.64,
        "volume": 10811,
        "tradeAmount": 294427490,
        "marketCap": 27270000000,
        "nav": 26679.05,
        "highPrice": 27530,
        "lowPrice": 26830,
        "openPrice": 26830,
        "date": "20260526",
        "sector": "기타"
      },
      {
        "code": "0051G0",
        "name": "SOL 미국원자력SMR",
        "price": 16620,
        "change": 275,
        "changeRate": 1.68,
        "volume": 357447,
        "tradeAmount": 5905033111,
        "marketCap": 240990000000,
        "nav": 16324.55,
        "highPrice": 16645,
        "lowPrice": 16445,
        "openPrice": 16500,
        "date": "20260526",
        "sector": "해외주식"
      },
      {
        "code": "0052D0",
        "name": "TIGER 코리아배당다우존스",
        "price": 16535,
        "change": -210,
        "changeRate": -1.25,
        "volume": 640561,
        "tradeAmount": 10708139987,
        "marketCap": 453885750000,
        "nav": 16636.61,
        "highPrice": 17130,
        "lowPrice": 16535,
        "openPrice": 17000,
        "date": "20260526",
        "sector": "커버드콜·월배당"
      },
      {
        "code": "0052S0",
        "name": "1Q 미국S&P500미국채혼합50액티브",
        "price": 12480,
        "change": -60,
        "changeRate": -0.48,
        "volume": 416557,
        "tradeAmount": 5213655539,
        "marketCap": 279552000000,
        "nav": 12435.38,
        "highPrice": 12600,
        "lowPrice": 12465,
        "openPrice": 12545,
        "date": "20260526",
        "sector": "해외주식"
      },
      {
        "code": "0052T0",
        "name": "1Q 중단기회사채(A-이상)액티브",
        "price": 50335,
        "change": 70,
        "changeRate": 0.14,
        "volume": 19909,
        "tradeAmount": 1001687380,
        "marketCap": 89495630000,
        "nav": 50328.47,
        "highPrice": 50335,
        "lowPrice": 50305,
        "openPrice": 50325,
        "date": "20260526",
        "sector": "채권"
      },
      {
        "code": "0053L0",
        "name": "TIGER 차이나휴머노이드로봇",
        "price": 14210,
        "change": 20,
        "changeRate": 0.14,
        "volume": 1522200,
        "tradeAmount": 21835145898,
        "marketCap": 410669000000,
        "nav": 14353.92,
        "highPrice": 14540,
        "lowPrice": 14085,
        "openPrice": 14315,
        "date": "20260526",
        "sector": "기타"
      },
      {
        "code": "0053M0",
        "name": "더제이 중소형포커스액티브",
        "price": 15860,
        "change": 100,
        "changeRate": 0.63,
        "volume": 366,
        "tradeAmount": 5828545,
        "marketCap": 7137000000,
        "nav": 15934.79,
        "highPrice": 16245,
        "lowPrice": 15835,
        "openPrice": 16245,
        "date": "20260526",
        "sector": "기타"
      },
      {
        "code": "0057H0",
        "name": "PLUS 미국S&P500미국채혼합50액티브",
        "price": 12550,
        "change": -60,
        "changeRate": -0.48,
        "volume": 75994,
        "tradeAmount": 956869674,
        "marketCap": 66515000000,
        "nav": 12518.6,
        "highPrice": 12640,
        "lowPrice": 12545,
        "openPrice": 12630,
        "date": "20260526",
        "sector": "해외주식"
      },
      {
        "code": "0060H0",
        "name": "TIGER 토탈월드스탁액티브",
        "price": 13670,
        "change": 60,
        "changeRate": 0.44,
        "volume": 106594,
        "tradeAmount": 1461153097,
        "marketCap": 388228000000,
        "nav": 13523.54,
        "highPrice": 13765,
        "lowPrice": 13640,
        "openPrice": 13640,
        "date": "20260526",
        "sector": "기타"
      },
      {
        "code": "0061Z0",
        "name": "RISE 단기특수은행채액티브",
        "price": 50600,
        "change": 0,
        "changeRate": 0,
        "volume": 5971,
        "tradeAmount": 302140805,
        "marketCap": 758797600000,
        "nav": 50600.94,
        "highPrice": 50605,
        "lowPrice": 50600,
        "openPrice": 50600,
        "date": "20260526",
        "sector": "원자재·금"
      },
      {
        "code": "0064K0",
        "name": "KODEX 금액티브",
        "price": 14250,
        "change": -100,
        "changeRate": -0.7,
        "volume": 204857,
        "tradeAmount": 2936760993,
        "marketCap": 227287500000,
        "nav": 14226.24,
        "highPrice": 14440,
        "lowPrice": 14245,
        "openPrice": 14430,
        "date": "20260526",
        "sector": "원자재·금"
      },
      {
        "code": "0065G0",
        "name": "KODEX 차이나테크TOP10",
        "price": 10465,
        "change": 5,
        "changeRate": 0.05,
        "volume": 117506,
        "tradeAmount": 1234733213,
        "marketCap": 33488000000,
        "nav": 10459.97,
        "highPrice": 10600,
        "lowPrice": 10345,
        "openPrice": 10495,
        "date": "20260526",
        "sector": "기타"
      },
      {
        "code": "0066W0",
        "name": "SOL 국제금",
        "price": 14435,
        "change": -75,
        "changeRate": -0.52,
        "volume": 124805,
        "tradeAmount": 1806170007,
        "marketCap": 114758250000,
        "nav": 14373.84,
        "highPrice": 14635,
        "lowPrice": 14410,
        "openPrice": 14605,
        "date": "20260526",
        "sector": "원자재·금"
      },
      {
        "code": "0067V0",
        "name": "TIGER 차이나글로벌리더스TOP3+",
        "price": 12015,
        "change": 20,
        "changeRate": 0.17,
        "volume": 48319,
        "tradeAmount": 584595624,
        "marketCap": 58873500000,
        "nav": 12384.17,
        "highPrice": 12200,
        "lowPrice": 11955,
        "openPrice": 12160,
        "date": "20260526",
        "sector": "기타"
      },
      {
        "code": "0067Y0",
        "name": "TIGER 차이나AI소프트웨어",
        "price": 13765,
        "change": 190,
        "changeRate": 1.4,
        "volume": 42184,
        "tradeAmount": 573316218,
        "marketCap": 17894500000,
        "nav": 13586.62,
        "highPrice": 13960,
        "lowPrice": 13165,
        "openPrice": 13585,
        "date": "20260526",
        "sector": "AI·데이터"
      },
      {
        "code": "0068M0",
        "name": "KODEX 미국S&P500버퍼6월액티브",
        "price": 12265,
        "change": -135,
        "changeRate": -1.09,
        "volume": 221,
        "tradeAmount": 2732910,
        "marketCap": 61325000000,
        "nav": 12605.87,
        "highPrice": 12485,
        "lowPrice": 12265,
        "openPrice": 12400,
        "date": "20260526",
        "sector": "해외주식"
      },
      {
        "code": "0069M0",
        "name": "1Q 미국나스닥100",
        "price": 14835,
        "change": 10,
        "changeRate": 0.07,
        "volume": 227029,
        "tradeAmount": 3380212013,
        "marketCap": 173569500000,
        "nav": 14703.59,
        "highPrice": 14975,
        "lowPrice": 14830,
        "openPrice": 14970,
        "date": "20260526",
        "sector": "해외주식"
      },
      {
        "code": "0072R0",
        "name": "TIGER KRX금현물",
        "price": 14400,
        "change": -105,
        "changeRate": -0.72,
        "volume": 1480578,
        "tradeAmount": 21422952605,
        "marketCap": 1430640000000,
        "nav": 14552.74,
        "highPrice": 14605,
        "lowPrice": 14385,
        "openPrice": 14565,
        "date": "20260526",
        "sector": "원자재·금"
      },
      {
        "code": "0073X0",
        "name": "FOCUS 알리바바미국채커버드콜혼합",
        "price": 10580,
        "change": -5,
        "changeRate": -0.05,
        "volume": 13559,
        "tradeAmount": 143317873,
        "marketCap": 5819000000,
        "nav": 10546.83,
        "highPrice": 10630,
        "lowPrice": 10485,
        "openPrice": 10585,
        "date": "20260526",
        "sector": "커버드콜·월배당"
      },
      {
        "code": "0074K0",
        "name": "KoAct K수출핵심기업TOP30액티브",
        "price": 22210,
        "change": 730,
        "changeRate": 3.4,
        "volume": 305560,
        "tradeAmount": 6774385465,
        "marketCap": 188785000000,
        "nav": 22191.04,
        "highPrice": 22370,
        "lowPrice": 21775,
        "openPrice": 22180,
        "date": "20260526",
        "sector": "기타"
      },
      {
        "code": "0078V0",
        "name": "PLUS 미국로보택시",
        "price": 11475,
        "change": -45,
        "changeRate": -0.39,
        "volume": 3372,
        "tradeAmount": 38834329,
        "marketCap": 7458750000,
        "nav": 11399.85,
        "highPrice": 11575,
        "lowPrice": 11460,
        "openPrice": 11540,
        "date": "20260526",
        "sector": "해외주식"
      },
      {
        "code": "0079X0",
        "name": "ACE BYD밸류체인액티브",
        "price": 12475,
        "change": 60,
        "changeRate": 0.48,
        "volume": 4233,
        "tradeAmount": 52582190,
        "marketCap": 3742500000,
        "nav": 12211.43,
        "highPrice": 13275,
        "lowPrice": 12195,
        "openPrice": 13275,
        "date": "20260526",
        "sector": "기타"
      },
      {
        "code": "0080G0",
        "name": "KODEX 방산TOP10",
        "price": 14075,
        "change": 305,
        "changeRate": 2.21,
        "volume": 6035980,
        "tradeAmount": 83970489691,
        "marketCap": 575667500000,
        "nav": 14074.32,
        "highPrice": 14190,
        "lowPrice": 13530,
        "openPrice": 13810,
        "date": "20260526",
        "sector": "방산"
      },
      {
        "code": "0080X0",
        "name": "SOL 미국S&P500미국채혼합50",
        "price": 11885,
        "change": -55,
        "changeRate": -0.46,
        "volume": 120153,
        "tradeAmount": 1432059989,
        "marketCap": 64179000000,
        "nav": 11862.56,
        "highPrice": 11995,
        "lowPrice": 11575,
        "openPrice": 11575,
        "date": "20260526",
        "sector": "해외주식"
      },
      {
        "code": "0080Y0",
        "name": "SOL 조선TOP3플러스레버리지",
        "price": 21800,
        "change": 2535,
        "changeRate": 13.16,
        "volume": 2599490,
        "tradeAmount": 55583470000,
        "marketCap": 222360000000,
        "nav": 21655.42,
        "highPrice": 22785,
        "lowPrice": 19740,
        "openPrice": 19930,
        "date": "20260526",
        "sector": "조선"
      },
      {
        "code": "0082F0",
        "name": "HANARO 유럽방산",
        "price": 10840,
        "change": 325,
        "changeRate": 3.09,
        "volume": 1366,
        "tradeAmount": 14879580,
        "marketCap": 9214000000,
        "nav": 10890.33,
        "highPrice": 10930,
        "lowPrice": 10840,
        "openPrice": 10855,
        "date": "20260526",
        "sector": "방산"
      },
      {
        "code": "0082V0",
        "name": "KODEX TDF2060액티브 적격",
        "price": 12395,
        "change": 20,
        "changeRate": 0.16,
        "volume": 348204,
        "tradeAmount": 4335533883,
        "marketCap": 165473250000,
        "nav": 12301.97,
        "highPrice": 12550,
        "lowPrice": 12395,
        "openPrice": 12415,
        "date": "20260526",
        "sector": "기타"
      },
      {
        "code": "0083S0",
        "name": "1Q 미국메디컬AI",
        "price": 10000,
        "change": -60,
        "changeRate": -0.6,
        "volume": 164908,
        "tradeAmount": 1651203559,
        "marketCap": 41000000000,
        "nav": 9903.36,
        "highPrice": 10060,
        "lowPrice": 9985,
        "openPrice": 10045,
        "date": "20260526",
        "sector": "AI·데이터"
      },
      {
        "code": "0084D0",
        "name": "KIWOOM 미국테크100월간목표헤지액티브",
        "price": 12505,
        "change": -35,
        "changeRate": -0.28,
        "volume": 1295,
        "tradeAmount": 16273640,
        "marketCap": 10004000000,
        "nav": 12529.73,
        "highPrice": 12590,
        "lowPrice": 12505,
        "openPrice": 12570,
        "date": "20260526",
        "sector": "해외주식"
      },
      {
        "code": "0084E0",
        "name": "KIWOOM 미국대형주500월간목표헤지액티브",
        "price": 11055,
        "change": -120,
        "changeRate": -1.07,
        "volume": 139,
        "tradeAmount": 1543290,
        "marketCap": 17135250000,
        "nav": 11169.3,
        "highPrice": 11285,
        "lowPrice": 11055,
        "openPrice": 11200,
        "date": "20260526",
        "sector": "해외주식"
      },
      {
        "code": "0085N0",
        "name": "ACE 미국10년국채액티브(H)",
        "price": 9905,
        "change": 50,
        "changeRate": 0.51,
        "volume": 188011,
        "tradeAmount": 1863546991,
        "marketCap": 31696000000,
        "nav": 9886.82,
        "highPrice": 9925,
        "lowPrice": 9895,
        "openPrice": 9920,
        "date": "20260526",
        "sector": "해외주식"
      },
      {
        "code": "0085P0",
        "name": "ACE 미국10년국채액티브",
        "price": 10835,
        "change": -40,
        "changeRate": -0.37,
        "volume": 361352,
        "tradeAmount": 3936442376,
        "marketCap": 94264500000,
        "nav": 10815.98,
        "highPrice": 10930,
        "lowPrice": 10835,
        "openPrice": 10930,
        "date": "20260526",
        "sector": "해외주식"
      },
      {
        "code": "0086B0",
        "name": "TIGER 리츠부동산인프라TOP10액티브",
        "price": 10245,
        "change": 65,
        "changeRate": 0.64,
        "volume": 178270,
        "tradeAmount": 1836510728,
        "marketCap": 61470000000,
        "nav": 10320.34,
        "highPrice": 10585,
        "lowPrice": 10180,
        "openPrice": 10280,
        "date": "20260526",
        "sector": "기타"
      },
      {
        "code": "0086C0",
        "name": "TIGER 리츠부동산인프라10채권혼합액티브",
        "price": 10145,
        "change": 10,
        "changeRate": 0.1,
        "volume": 105335,
        "tradeAmount": 1070955467,
        "marketCap": 17753750000,
        "nav": 10181.34,
        "highPrice": 10220,
        "lowPrice": 10040,
        "openPrice": 10135,
        "date": "20260526",
        "sector": "채권"
      },
      {
        "code": "0087F0",
        "name": "ACE 차이나AI빅테크TOP2+액티브",
        "price": 13875,
        "change": 290,
        "changeRate": 2.13,
        "volume": 6818,
        "tradeAmount": 94501811,
        "marketCap": 13181250000,
        "nav": 13740.32,
        "highPrice": 13990,
        "lowPrice": 13675,
        "openPrice": 13675,
        "date": "20260526",
        "sector": "AI·데이터"
      },
      {
        "code": "0088N0",
        "name": "WON K-글로벌수급상위",
        "price": 14210,
        "change": 55,
        "changeRate": 0.39,
        "volume": 22751,
        "tradeAmount": 327527817,
        "marketCap": 24157000000,
        "nav": 14292.7,
        "highPrice": 14620,
        "lowPrice": 14210,
        "openPrice": 14500,
        "date": "20260526",
        "sector": "기타"
      },
      {
        "code": "0089B0",
        "name": "PLUS 미국나스닥100미국채혼합50",
        "price": 12235,
        "change": -45,
        "changeRate": -0.37,
        "volume": 76877,
        "tradeAmount": 944501800,
        "marketCap": 29364000000,
        "nav": 12181.45,
        "highPrice": 12330,
        "lowPrice": 12235,
        "openPrice": 12330,
        "date": "20260526",
        "sector": "해외주식"
      }
    ],
    "byVolume": [
      {
        "code": "0080G0",
        "name": "KODEX 방산TOP10",
        "price": 14075,
        "change": 305,
        "changeRate": 2.21,
        "volume": 6035980,
        "tradeAmount": 83970489691,
        "marketCap": 575667500000,
        "nav": 14074.32,
        "highPrice": 14190,
        "lowPrice": 13530,
        "openPrice": 13810,
        "date": "20260526",
        "sector": "방산"
      },
      {
        "code": "0080Y0",
        "name": "SOL 조선TOP3플러스레버리지",
        "price": 21800,
        "change": 2535,
        "changeRate": 13.16,
        "volume": 2599490,
        "tradeAmount": 55583470000,
        "marketCap": 222360000000,
        "nav": 21655.42,
        "highPrice": 22785,
        "lowPrice": 19740,
        "openPrice": 19930,
        "date": "20260526",
        "sector": "조선"
      },
      {
        "code": "0023A0",
        "name": "SOL 미국양자컴퓨팅TOP10",
        "price": 38440,
        "change": 1980,
        "changeRate": 5.43,
        "volume": 1591591,
        "tradeAmount": 61403715408,
        "marketCap": 584288000000,
        "nav": 37529.93,
        "highPrice": 39235,
        "lowPrice": 37835,
        "openPrice": 38800,
        "date": "20260526",
        "sector": "해외주식"
      },
      {
        "code": "0053L0",
        "name": "TIGER 차이나휴머노이드로봇",
        "price": 14210,
        "change": 20,
        "changeRate": 0.14,
        "volume": 1522200,
        "tradeAmount": 21835145898,
        "marketCap": 410669000000,
        "nav": 14353.92,
        "highPrice": 14540,
        "lowPrice": 14085,
        "openPrice": 14315,
        "date": "20260526",
        "sector": "기타"
      },
      {
        "code": "0072R0",
        "name": "TIGER KRX금현물",
        "price": 14400,
        "change": -105,
        "changeRate": -0.72,
        "volume": 1480578,
        "tradeAmount": 21422952605,
        "marketCap": 1430640000000,
        "nav": 14552.74,
        "highPrice": 14605,
        "lowPrice": 14385,
        "openPrice": 14565,
        "date": "20260526",
        "sector": "원자재·금"
      },
      {
        "code": "0046A0",
        "name": "TIGER 미국초단기(3개월이하)국채",
        "price": 10420,
        "change": -90,
        "changeRate": -0.86,
        "volume": 1425877,
        "tradeAmount": 14916364651,
        "marketCap": 375015800000,
        "nav": 10419.38,
        "highPrice": 10495,
        "lowPrice": 10420,
        "openPrice": 10480,
        "date": "20260526",
        "sector": "해외주식"
      },
      {
        "code": "0048K0",
        "name": "KODEX 차이나휴머노이드로봇",
        "price": 12280,
        "change": -35,
        "changeRate": -0.28,
        "volume": 1321065,
        "tradeAmount": 16374761993,
        "marketCap": 259108000000,
        "nav": 12223.61,
        "highPrice": 12700,
        "lowPrice": 12130,
        "openPrice": 12405,
        "date": "20260526",
        "sector": "기타"
      },
      {
        "code": "0019K0",
        "name": "TIME 미국나스닥100채권혼합50액티브",
        "price": 14325,
        "change": 30,
        "changeRate": 0.21,
        "volume": 1270509,
        "tradeAmount": 18281583539,
        "marketCap": 348813750000,
        "nav": 14179.47,
        "highPrice": 14690,
        "lowPrice": 14275,
        "openPrice": 14495,
        "date": "20260526",
        "sector": "해외주식"
      },
      {
        "code": "0040Y0",
        "name": "SOL 팔란티어커버드콜OTM채권혼합",
        "price": 8790,
        "change": 20,
        "changeRate": 0.23,
        "volume": 1134387,
        "tradeAmount": 9973154412,
        "marketCap": 394231500000,
        "nav": 8724.14,
        "highPrice": 8825,
        "lowPrice": 8770,
        "openPrice": 8770,
        "date": "20260526",
        "sector": "AI·데이터"
      },
      {
        "code": "0015B0",
        "name": "KoAct 미국나스닥성장기업액티브",
        "price": 23645,
        "change": 105,
        "changeRate": 0.45,
        "volume": 1087006,
        "tradeAmount": 25848837105,
        "marketCap": 651419750000,
        "nav": 23234.16,
        "highPrice": 24025,
        "lowPrice": 23605,
        "openPrice": 23765,
        "date": "20260526",
        "sector": "해외주식"
      }
    ],
    "byGain": [
      {
        "code": "0080Y0",
        "name": "SOL 조선TOP3플러스레버리지",
        "price": 21800,
        "change": 2535,
        "changeRate": 13.16,
        "volume": 2599490,
        "tradeAmount": 55583470000,
        "marketCap": 222360000000,
        "nav": 21655.42,
        "highPrice": 22785,
        "lowPrice": 19740,
        "openPrice": 19930,
        "date": "20260526",
        "sector": "조선"
      },
      {
        "code": "0005G0",
        "name": "IBK K-AI반도체코어테크",
        "price": 62915,
        "change": 5715,
        "changeRate": 9.99,
        "volume": 202811,
        "tradeAmount": 12734934939,
        "marketCap": 191890750000,
        "nav": 62614.82,
        "highPrice": 63720,
        "lowPrice": 60335,
        "openPrice": 60740,
        "date": "20260526",
        "sector": "AI·데이터"
      },
      {
        "code": "0043Y0",
        "name": "TIME 차이나AI테크액티브",
        "price": 24450,
        "change": 1355,
        "changeRate": 5.87,
        "volume": 642216,
        "tradeAmount": 15645588631,
        "marketCap": 348412500000,
        "nav": 23783.58,
        "highPrice": 24750,
        "lowPrice": 23800,
        "openPrice": 23900,
        "date": "20260526",
        "sector": "AI·데이터"
      },
      {
        "code": "0020H0",
        "name": "KoAct 글로벌양자컴퓨팅액티브",
        "price": 30775,
        "change": 1680,
        "changeRate": 5.77,
        "volume": 269924,
        "tradeAmount": 8357334879,
        "marketCap": 55395000000,
        "nav": 29886.24,
        "highPrice": 36215,
        "lowPrice": 30440,
        "openPrice": 32000,
        "date": "20260526",
        "sector": "기타"
      },
      {
        "code": "0023A0",
        "name": "SOL 미국양자컴퓨팅TOP10",
        "price": 38440,
        "change": 1980,
        "changeRate": 5.43,
        "volume": 1591591,
        "tradeAmount": 61403715408,
        "marketCap": 584288000000,
        "nav": 37529.93,
        "highPrice": 39235,
        "lowPrice": 37835,
        "openPrice": 38800,
        "date": "20260526",
        "sector": "해외주식"
      }
    ],
    "byLoss": [
      {
        "code": "0001P0",
        "name": "마이티 바이오시밀러&CDMO액티브",
        "price": 11500,
        "change": -155,
        "changeRate": -1.33,
        "volume": 15141,
        "tradeAmount": 175843425,
        "marketCap": 12880000000,
        "nav": 11542.59,
        "highPrice": 11895,
        "lowPrice": 11485,
        "openPrice": 11825,
        "date": "20260526",
        "sector": "기타"
      },
      {
        "code": "0052D0",
        "name": "TIGER 코리아배당다우존스",
        "price": 16535,
        "change": -210,
        "changeRate": -1.25,
        "volume": 640561,
        "tradeAmount": 10708139987,
        "marketCap": 453885750000,
        "nav": 16636.61,
        "highPrice": 17130,
        "lowPrice": 16535,
        "openPrice": 17000,
        "date": "20260526",
        "sector": "커버드콜·월배당"
      },
      {
        "code": "0018C0",
        "name": "PLUS 고배당주위클리고정커버드콜",
        "price": 12020,
        "change": -150,
        "changeRate": -1.23,
        "volume": 300324,
        "tradeAmount": 3626872722,
        "marketCap": 96160000000,
        "nav": 12113.01,
        "highPrice": 12350,
        "lowPrice": 12000,
        "openPrice": 12285,
        "date": "20260526",
        "sector": "커버드콜·월배당"
      },
      {
        "code": "0068M0",
        "name": "KODEX 미국S&P500버퍼6월액티브",
        "price": 12265,
        "change": -135,
        "changeRate": -1.09,
        "volume": 221,
        "tradeAmount": 2732910,
        "marketCap": 61325000000,
        "nav": 12605.87,
        "highPrice": 12485,
        "lowPrice": 12265,
        "openPrice": 12400,
        "date": "20260526",
        "sector": "해외주식"
      },
      {
        "code": "0084E0",
        "name": "KIWOOM 미국대형주500월간목표헤지액티브",
        "price": 11055,
        "change": -120,
        "changeRate": -1.07,
        "volume": 139,
        "tradeAmount": 1543290,
        "marketCap": 17135250000,
        "nav": 11169.3,
        "highPrice": 11285,
        "lowPrice": 11055,
        "openPrice": 11200,
        "date": "20260526",
        "sector": "해외주식"
      }
    ],
    "sectorFlow": [
      {
        "sector": "조선",
        "count": 1,
        "avgChangeRate": 13.16,
        "totalAmount": 55583470000
      },
      {
        "sector": "방산",
        "count": 2,
        "avgChangeRate": 2.65,
        "totalAmount": 83985369271
      },
      {
        "sector": "AI·데이터",
        "count": 13,
        "avgChangeRate": 1.6,
        "totalAmount": 50542234169
      },
      {
        "sector": "기타",
        "count": 29,
        "avgChangeRate": 1.12,
        "totalAmount": 123115246569
      },
      {
        "sector": "해외주식",
        "count": 34,
        "avgChangeRate": 0.48,
        "totalAmount": 179377592232
      },
      {
        "sector": "채권",
        "count": 6,
        "avgChangeRate": 0.11,
        "totalAmount": 2874191504
      },
      {
        "sector": "커버드콜·월배당",
        "count": 10,
        "avgChangeRate": -0.16,
        "totalAmount": 29326793864
      },
      {
        "sector": "2차전지",
        "count": 1,
        "avgChangeRate": -0.39,
        "totalAmount": 20562489460
      },
      {
        "sector": "원자재·금",
        "count": 4,
        "avgChangeRate": -0.48,
        "totalAmount": 26468024410
      }
    ]
  }
}